__init__.py
domains/__init__.py
domains/extentive_motif_breakage_space.py
domains/hamming_space.py
domains/motif_breakage_space.py
domains/motif_hyphen_space.py
domains/motif_production_space.py
domains/motif_space.py
domains/time_space.py
domains/trajectory_space.py
get/__init__.py
get/alphabet.py
get/motif_breakage_rate_constants.py
get/motif_production_rate_constants.py
get/strand_length_distribution.py
get/strand_motifs_productions_trajectory.py
get/strand_motifs_productions_trajectory_ensemble.py
get/strand_motifs_trajectory.py
get/strand_motifs_trajectory_ensemble.py
get/strand_reactor_parameters.py
infer/__init__.py
infer/_rates_utils.py
infer/_smooth_rate_clipping.py
infer/collisions.py
infer/dissociation_constant.py
infer/effective_ligation_rates_from_parameters.py
infer/fourmer_breakage_rates.py
infer/fourmer_mass_correction.py
infer/fourmer_production_rates.py
infer/fourmer_trajectory_from_rate_constants.py
infer/mean_length.py
infer/motif_breakage_rate_constants_from_strand_reactor_parameters.py
infer/motif_concentration_trajectory.py
infer/motif_concentration_vector.py
infer/motif_production_rate_constants_extension_matrix.py
infer/motif_production_rate_constants_from_strand_reactor_parameters.py
infer/motif_production_rates.py
infer/motif_production_transition_kernel.py
infer/onset.py
infer/total_mass.py
infer/zebraness.py
morsaik/__init__.py
morsaik/domains/__init__.py
morsaik/domains/extentive_motif_breakage_space.py
morsaik/domains/hamming_space.py
morsaik/domains/motif_breakage_space.py
morsaik/domains/motif_hyphen_space.py
morsaik/domains/motif_production_space.py
morsaik/domains/motif_space.py
morsaik/domains/time_space.py
morsaik/domains/trajectory_space.py
morsaik/get/__init__.py
morsaik/get/alphabet.py
morsaik/get/motif_breakage_rate_constants.py
morsaik/get/motif_production_rate_constants.py
morsaik/get/strand_length_distribution.py
morsaik/get/strand_motifs_productions_trajectory.py
morsaik-0.1.4.dist-info/licenses/LICENSE
morsaik-0.1.4.dist-info/METADATA
morsaik-0.1.4.dist-info/WHEEL
morsaik-0.1.4.dist-info/top_level.txt
morsaik-0.1.4.dist-info/RECORD
