Metadata-Version: 2.4
Name: morsaik
Version: 0.1.4
Summary: Sequence Motif Reactor Simulation, Analysis and Inference Kit.
Author-email: Johannes Harth-Kitzerow <jharthki@mpa-garching.mpg.de>
License-Expression: GPL-3.0-or-later
Project-URL: Homepage, https://github.com/joharkit/morsaik
Project-URL: Issues, https://github.com/joharkit/morsaik/issues
Classifier: Programming Language :: Python :: 3
Classifier: Operating System :: OS Independent
Requires-Python: <4.0,>=3.10
License-File: LICENSE
Requires-Dist: scipy>=1.15.3
Requires-Dist: nifty8>=8.5
Requires-Dist: jax
Requires-Dist: jaxlib
Requires-Dist: matplotlib
Requires-Dist: units>=0.07
Requires-Dist: diffrax==0.7.0
Requires-Dist: sphinx<9.0.0,>=8.1.3
Requires-Dist: pyyaml<7.0.0,>=6.0.2
Requires-Dist: myst-parser<5.0.0,>=4.0.0
Requires-Dist: pydata-sphinx-theme<0.17.0,>=0.16.1
Provides-Extra: docs
Requires-Dist: sphinx; extra == "docs"
Requires-Dist: pyyaml; extra == "docs"
Requires-Dist: myst_parser; extra == "docs"
Requires-Dist: pydata-sphinx-theme; extra == "docs"
Dynamic: license-file
